LICENSE
MANIFEST.in
README.md
setup.py
dfitspy/__info__.py
dfitspy/__init__.py
dfitspy/__main__.py
dfitspy/cli.py
dfitspy/display.py
dfitspy/get_files_and_keys.py
dfitspy/readfits.py
dfitspy/tests.py
dfitspy.egg-info/PKG-INFO
dfitspy.egg-info/SOURCES.txt
dfitspy.egg-info/dependency_links.txt
dfitspy.egg-info/entry_points.txt
dfitspy.egg-info/requires.txt
dfitspy.egg-info/top_level.txt
dfitspy/docs/.nojekyll
dfitspy/docs/Makefile
dfitspy/docs/index.html
dfitspy/docs/logo.txt
dfitspy/docs/build/doctrees/apidoc.doctree
dfitspy/docs/build/doctrees/dfits_fitsort.doctree
dfitspy/docs/build/doctrees/dfitspy.doctree
dfitspy/docs/build/doctrees/environment.pickle
dfitspy/docs/build/doctrees/index.doctree
dfitspy/docs/build/doctrees/installation.doctree
dfitspy/docs/build/doctrees/modules.doctree
dfitspy/docs/build/doctrees/usage.doctree
dfitspy/docs/build/doctrees/usage_module.doctree
dfitspy/docs/build/html/.buildinfo
dfitspy/docs/build/html/.nojekyll
dfitspy/docs/build/html/apidoc.html
dfitspy/docs/build/html/dfits_fitsort.html
dfitspy/docs/build/html/dfitspy.html
dfitspy/docs/build/html/genindex.html
dfitspy/docs/build/html/index.html
dfitspy/docs/build/html/installation.html
dfitspy/docs/build/html/modules.html
dfitspy/docs/build/html/objects.inv
dfitspy/docs/build/html/py-modindex.html
dfitspy/docs/build/html/search.html
dfitspy/docs/build/html/searchindex.js
dfitspy/docs/build/html/usage.html
dfitspy/docs/build/html/usage_module.html
dfitspy/docs/build/html/_images/dfitspy.png
dfitspy/docs/build/html/_images/logo.png
dfitspy/docs/build/html/_sources/apidoc.rst.txt
dfitspy/docs/build/html/_sources/dfits_fitsort.rst.txt
dfitspy/docs/build/html/_sources/dfitspy.rst.txt
dfitspy/docs/build/html/_sources/index.rst.txt
dfitspy/docs/build/html/_sources/installation.rst.txt
dfitspy/docs/build/html/_sources/modules.rst.txt
dfitspy/docs/build/html/_sources/usage.rst.txt
dfitspy/docs/build/html/_sources/usage_module.rst.txt
dfitspy/docs/build/html/_static/ajax-loader.gif
dfitspy/docs/build/html/_static/alabaster.css
dfitspy/docs/build/html/_static/basic.css
dfitspy/docs/build/html/_static/comment-bright.png
dfitspy/docs/build/html/_static/comment-close.png
