Metadata-Version: 1.2
Name: dfitspy
Version: 20.8.1
Summary: A dfits|fitsio implementation in python
Home-page: https://astrom-tom.github.io/dfitspy/build/html/index.html
Author: Romain Thomas
License: GNU GPL v3
Platform: UNKNOWN
Requires-Python: >=3.6
